st_draggable_list/__init__.py
st_draggable_list/frontend/build/asset-manifest.json
st_draggable_list/frontend/build/bootstrap.min.css
st_draggable_list/frontend/build/index.html
st_draggable_list/frontend/build/static/js/2.fa90537d.chunk.js
st_draggable_list/frontend/build/static/js/2.fa90537d.chunk.js.LICENSE.txt
st_draggable_list/frontend/build/static/js/2.fa90537d.chunk.js.map
st_draggable_list/frontend/build/static/js/main.73bf5aa6.chunk.js
st_draggable_list/frontend/build/static/js/main.73bf5aa6.chunk.js.map
st_draggable_list/frontend/build/static/js/runtime-main.6c2dc79e.js
st_draggable_list/frontend/build/static/js/runtime-main.6c2dc79e.js.map
streamlit_draggable_list_39-0.0.1.dist-info/LICENSE
streamlit_draggable_list_39-0.0.1.dist-info/METADATA
streamlit_draggable_list_39-0.0.1.dist-info/WHEEL
streamlit_draggable_list_39-0.0.1.dist-info/top_level.txt
streamlit_draggable_list_39-0.0.1.dist-info/RECORD
