Metadata-Version: 2.1
Name: streamlit-draggable-list-39
Version: 0.0.1
Summary: Streamlit component of draggable list
Home-page: 
Author: Mohd Alomar
Author-email: mohd.talat@hotmail.com
Requires-Python: >=3.6
License-File: LICENSE
Requires-Dist: streamlit (>=0.63)
